{
  "sections": {
    "main_product": {
      "type": "en-product",
      "blocks": {
        "title": {
          "type": "title",
          "settings": {
          }
        },
        "vendor": {
          "type": "vendor",
          "settings": {
          }
        },
        "price": {
          "type": "price",
          "settings": {
          }
        },
        "ec32b341-80ad-4104-bda2-f7a389fb2237": {
          "type": "description",
          "settings": {
          }
        },
        "variant_selector": {
          "type": "variant_selector",
          "settings": {
          }
        },
        "quantity": {
          "type": "quantity",
          "settings": {
          }
        },
        "sku": {
          "type": "sku",
          "settings": {
          }
        },
        "checkout_buttons": {
          "type": "checkout_buttons",
          "settings": {
            "show_dynamic_checkout": true
          }
        }
      },
      "block_order": [
        "title",
        "vendor",
        "price",
        "ec32b341-80ad-4104-bda2-f7a389fb2237",
        "variant_selector",
        "quantity",
        "sku",
        "checkout_buttons"
      ],
      "settings": {
        "media_position": "left",
        "media_width": "medium"
      }
    },
    "recommended_products": {
      "type": "product-recommendations",
      "settings": {
      }
    }
  },
  "order": [
    "main_product",
    "recommended_products"
  ]
}
